{"cameraMode":{"drawMode":0,"name":"Shaded","section":"Shading Mode"},"sceneLighting":true,"audioPlay":false,"sceneViewState":{"showFog":true,"showMaterialUpdate":false,"showSkybox":true,"showFlares":true,"showImageEffects":true,"showParticleSystems":true,"showVisualEffectGraphs":true,"m_FxEnabled":true},"in2DMode":false,"pivot":{"x":38.62554168701172,"y":5.983780384063721,"z":55.990596771240237},"rotation":{"x":-0.1703462153673172,"y":0.7999739050865173,"z":-0.2676126956939697,"w":-0.5093652606010437},"size":4.072859764099121,"orthographic":false}